uglychain/__init__.py
uglychain/client.py
uglychain/config.py
uglychain/console/__init__.py
uglychain/console/base.py
uglychain/console/memory.py
uglychain/console/rich.py
uglychain/console/simple.py
uglychain/llm.py
uglychain/load.py
uglychain/plan/__init__.py
uglychain/plan/plan.py
uglychain/plan/prompt.py
uglychain/prompt.py
uglychain/react/__init__.py
uglychain/react/action.py
uglychain/react/base.py
uglychain/react/core.py
uglychain/react/default.py
uglychain/react/get_process.py
uglychain/react/prompt.py
uglychain/schema.py
uglychain/session.py
uglychain/structured.py
uglychain/think.py
uglychain/tools/.gitignore
uglychain/tools/__init__.py
uglychain/tools/core/__init__.py
uglychain/tools/core/base_tool.py
uglychain/tools/core/mcp.py
uglychain/tools/core/schema.py
uglychain/tools/core/tool.py
uglychain/tools/core/tool_manager.py
uglychain/tools/providers/browser_use/__init__.py
uglychain/tools/providers/browser_use/browser.py
uglychain/tools/providers/browser_use/buildDomTree.js
uglychain/tools/providers/browser_use/context.py
uglychain/tools/providers/browser_use/core.py
uglychain/tools/providers/browser_use/dom.py
uglychain/tools/providers/browser_use/state.py
uglychain/tools/providers/coder.py
uglychain/tools/providers/default.py
uglychain/tools/providers/final_answer.py
uglychain/tools/utils/__init__.py
uglychain/tools/utils/mcp_client.py
uglychain/tools/utils/schema_utils.py
uglychain/utils/__init__.py
uglychain/utils/_load_utils.py
uglychain/utils/_response_parser.py
uglychain/utils/fastapi_wrappers.py
uglychain/utils/message_bus.py
uglychain/utils/retry.py
uglychain/utils/singleton.py
uglychain/utils/stream.py
uglychain-1.6.6.dist-info/WHEEL
uglychain-1.6.6.dist-info/METADATA
uglychain-1.6.6.dist-info/RECORD
