Metadata-Version: 2.3
Name: uglychain
Version: 1.6.6
Summary: ⚡ UglyChain：更好用的 LLM 应用构建工具 ⚡
Author: Uglyboy
Author-email: Uglyboy <uglyboy@uglyboy.cn>
License: MIT
Requires-Dist: pydantic>=2.0.0
Requires-Dist: mcp>=1.2.0
Requires-Dist: ruamel-yaml>=0.18.10
Requires-Dist: blinker>=1.9.0
Requires-Dist: aisuite>=0.1.11
Requires-Dist: openai>=1.70.0
Requires-Dist: docstring-parser>=0.16
Requires-Dist: playwright>=1.50.0 ; extra == 'browser'
Requires-Dist: unidiff>=0.7.5 ; extra == 'code'
Requires-Dist: rich>=14.0.0 ; extra == 'rich'
Requires-Python: >=3.13
Provides-Extra: browser
Provides-Extra: code
Provides-Extra: rich
